dotmapini/__init__.py
dotmapini/exceptions.py
dotmapini-1.0.4.dist-info/LICENSE
dotmapini-1.0.4.dist-info/METADATA
dotmapini-1.0.4.dist-info/WHEEL
dotmapini-1.0.4.dist-info/top_level.txt
dotmapini-1.0.4.dist-info/RECORD
