Metadata-Version: 2.1
Name: dotmapini
Version: 1.0.4
Summary: Package allow configuration and section's option values of .ini file to be called as attributes, where the section and option are separated by dot notation.
Author-email: Vladislav Anisimov <pan.vlados.w@gmail.com>
License: MIT License
Project-URL: repository, https://github.com/pan-vlados/dotmapini
Classifier: Programming Language :: Python :: 3
Classifier: License :: OSI Approved :: MIT License
Classifier: Operating System :: OS Independent
Classifier: Topic :: Software Development :: Libraries :: Python Modules
Classifier: Topic :: Utilities
Requires-Python: >=3.8
License-File: LICENSE
